pwproxy-1.1.2.dist-info/METADATA
pwproxy-1.1.2.dist-info/WHEEL
pwproxy-1.1.2.dist-info/entry_points.txt
pwproxy/__init__.py
pwproxy/cli.py
pwproxy/function.py
pwproxy/run.py
pwproxy-1.1.2.dist-info/RECORD
