Metadata-Version: 2.1
Name: pwproxy
Version: 1.1.2
Summary: Implement the core functions of mitmproxy based on playwright: request interception, response tampering
Author-Email: gaochuang <895091550@qq.com>
License: MIT
Requires-Python: >=3.10
Requires-Dist: playwright>=1.33.0
Requires-Dist: pandas>=2.0.1
Requires-Dist: click>=8.1.3
